manuscript/__init__.py
manuscript/_pipeline.py
manuscript/__pycache__/__init__.cpython-310.pyc
manuscript/__pycache__/__init__.cpython-311.pyc
manuscript/__pycache__/_pipeline.cpython-311.pyc
manuscript/__pycache__/pipeline.cpython-310.pyc
manuscript/__pycache__/pipeline.cpython-311.pyc
manuscript/api/LIBRARY_STRUCTURE.md
manuscript/api/base.py
manuscript/api/__pycache__/base.cpython-311.pyc
manuscript/correctors/__init__.py
manuscript/correctors/__pycache__/__init__.cpython-311.pyc
manuscript/correctors/_charlm/__init__.py
manuscript/correctors/_charlm/config.py
manuscript/correctors/_charlm/dataset.py
manuscript/correctors/_charlm/model.py
manuscript/correctors/_charlm/train.py
manuscript/correctors/_charlm/utils.py
manuscript/correctors/_charlm/__pycache__/__init__.cpython-311.pyc
manuscript/data/DATA_MODEL.md
manuscript/data/__init__.py
manuscript/data/structures.py
manuscript/data/__pycache__/__init__.cpython-311.pyc
manuscript/data/__pycache__/structures.cpython-311.pyc
manuscript/detectors/__init__.py
manuscript/detectors/__pycache__/__init__.cpython-311.pyc
manuscript/detectors/__pycache__/_types.cpython-311.pyc
manuscript/detectors/__pycache__/types.cpython-311.pyc
manuscript/detectors/_east/__init__.py
manuscript/detectors/_east/dataset.py
manuscript/detectors/_east/east.py
manuscript/detectors/_east/lanms.py
manuscript/detectors/_east/loss.py
manuscript/detectors/_east/sam.py
manuscript/detectors/_east/train_utils.py
manuscript/detectors/_east/utils.py
manuscript/detectors/_east/__pycache__/__init__.cpython-311.pyc
manuscript/detectors/_east/__pycache__/__init__.cpython-312.pyc
manuscript/detectors/_east/__pycache__/dataset.cpython-311.pyc
manuscript/detectors/_east/__pycache__/east.cpython-311.pyc
manuscript/detectors/_east/__pycache__/edge_post.cpython-311.pyc
manuscript/detectors/_east/__pycache__/infer.cpython-311.pyc
manuscript/detectors/_east/__pycache__/lanms.clip_polygon_by_edge-25.py311.1.nbc
manuscript_ocr-0.1.10.dist-info/METADATA
manuscript_ocr-0.1.10.dist-info/WHEEL
manuscript_ocr-0.1.10.dist-info/top_level.txt
manuscript_ocr-0.1.10.dist-info/RECORD
